Metadata-Version: 2.4
Name: delfin-complat
Version: 1.0.8
Summary: Automated ORCA, xTB and CREST workflow for predicting preferred spin states and associated redox potentials.
Author: Maximilian Hartmann
License-Expression: LGPL-3.0-or-later
Project-URL: Homepage, https://github.com/ComPlat/DELFIN
Project-URL: Repository, https://github.com/ComPlat/DELFIN
Requires-Python: >=3.10
License-File: LICENSE
Requires-Dist: mendeleev>=0.14
Requires-Dist: psutil
Requires-Dist: ase>=3.22.0
Requires-Dist: numpy>=1.19.5
Requires-Dist: scipy>=1.6.0
Requires-Dist: matplotlib>=3.3.4
Requires-Dist: rdkit>=2023.3.1
Requires-Dist: openbabel-wheel>=3.1.0
Requires-Dist: python-docx>=0.8.11
Requires-Dist: pymol-open-source>=3.0.0
Provides-Extra: dev
Requires-Dist: pytest>=6.0; extra == "dev"
Requires-Dist: pytest-cov; extra == "dev"
Requires-Dist: black; extra == "dev"
Requires-Dist: flake8; extra == "dev"
Requires-Dist: ruff; extra == "dev"
Dynamic: license-file
